cfbuild/__init__.py
cfbuild/_attribute_values.py
cfbuild/_classes.py
cfbuild/_constants.py
cfbuild/_create_dataset.py
cfbuild/_create_nc.py
cfbuild/_create_ncml.py
cfbuild/_grid_mapping.py
cfbuild/_ncml_comments.py
cfbuild/_refresh_ncml.py
cfbuild/_variable_identification.py
cfbuild/cf-standard-name-table.xml
cfbuild-0.0.11.dist-info/LICENSE
cfbuild-0.0.11.dist-info/METADATA
cfbuild-0.0.11.dist-info/WHEEL
cfbuild-0.0.11.dist-info/top_level.txt
cfbuild-0.0.11.dist-info/RECORD
