Metadata-Version: 2.1
Name: cfbuild
Version: 0.0.11
Summary: Used for generating netCDF files compliant with CF Conventions or ACDD
Home-page: https://github.com/jenochjones/cfbuild
Author: J Enoch Jones
Author-email: jonenochjones@gmail.com
Classifier: Programming Language :: Python :: 3
Classifier: License :: OSI Approved :: MIT License
Classifier: Operating System :: OS Independent
License-File: LICENSE
Requires-Dist: lxml
Requires-Dist: isodate
Requires-Dist: cfunits
Requires-Dist: netCDF4
Requires-Dist: pyproj
